{
    "index": "/index.html",
    "assetGroups": [
        {
            "name": "do-not-do-app",
            "installMode": "prefetch",
            "resources": {
                "files": ["/favicon.ico", "/index.html", "/*.css", "/*.js", "/*.ttf", "/*.woff2"]
            }
        },
        {
            "name": "do-not-do-assets",
            "installMode": "lazy",
            "updateMode": "prefetch",
            "resources": {
                "files": ["/assets/**"]
            }
        }
    ]
}
